README.md
setup.py
lomas_core/__init__.py
lomas_core/constants.py
lomas_core/error_handler.py
lomas_core/instrumentation.py
lomas_core.egg-info/PKG-INFO
lomas_core.egg-info/SOURCES.txt
lomas_core.egg-info/dependency_links.txt
lomas_core.egg-info/requires.txt
lomas_core.egg-info/top_level.txt
lomas_core/models/__init__.py
lomas_core/models/collections.py
lomas_core/models/config.py
lomas_core/models/constants.py
lomas_core/models/exceptions.py
lomas_core/models/requests.py
lomas_core/models/requests_examples.py
lomas_core/models/responses.py
lomas_core/models/utils.py